{
  "clientes": [
    {
      "usuario": "DavidW",
      "contraseña": "contraseña123",
      "correo": "david.willams@user.com",
      "imagen_usuario": "src/images/davidWilliams.png"
    },
    {
      "usuario": "LeonidasOr",
      "contraseña": "clave456",
      "correo": "leo.orellana@user.com",
      "imagen_usuario": "src/images/LeoOrellana.png"
    },
    {
      "usuario": "CeciliaVal",
      "contraseña": "miclave",
      "correo": "cecilia.valenzuela@user.com",
      "imagen_usuario": "ruta/imagen3.jpg"
    },
    {
      "usuario": "JoaquinPard",
      "contraseña": "123456",
      "correo": "magnate456@user.com",
      "imagen_usuario": "ruta/imagen4.jpg"
    }
  ],
  "productos": [
    {
      "id": "prd01",
      "nombre": "Mate Burilado",
      "descripcion": "Los mates burilados son frutos de mate o calabaza ornamentados de forma artesanal con una técnica llamada burilado",
      "precio": 29.99,
      "detalles": "Detalles adicionales sobre el producto 1",
      "detalles_del_artesano": "Información del artesano sobre el producto",
      "parametros_personalizacion": {
        "Colores": [
          "rojo",
          "azul",
          "verde"
        ],
        "material": [
          "madera",
          "metal"
        ],
        "tamanio": [
          "Grande",
          "Mediano",
          "Pequeño"
        ],
        "gravado": "Detalles de gravado para el producto 1"
      },
      "tamaño": 10,
      "input_text": "Elige un color",
      "gravado": "Detalles de gravado para el producto 1",
      "categoria": "Categoría 1",
      "imagen": "src/images/mateBurilado.png",
      "imagenes_detalle": [
        "src/images/mate1.png"
      ],
      "autor": "LeonidasOr",
      "caracteristicas": [
        {
          "caracteristica_1": "Estilo: Escultura tradicional cuzqueña"
        },
        {
          "caracteristica_2": "Material: Piedra de andesita"
        },
        {
          "caracteristica_3": "Técnica: Talla a mano"
        },
        {
          "caracteristica_4": "Dimensiones: 30cm de altura, 20cm de ancho y 15cm de profundidad"
        },
        {
          "caracteristica_5": "Coloración: Tonalidades tierra y toques dorados"
        }
      ]
    },
    {
      "id": "prd02",
      "nombre": "Miel de abeja  ",
      "descripcion": "Miel 100% natural y real. Cosechada de manera artesanal en los Andes peruanos (sobre los 2500msnm). No ha sido pasteurizada, gracias a ello conserva todas sus propiedades terapéuticas. Contiene todos los componentes de la mierl rela: polen, propóleo, cera, jalea real, enzimas vivas.",
      "precio": 12.99,
      "detalles": "Detalles adicionales sobre el producto 1",
      "detalles_del_artesano": "Miel 100% natural y real. Cosechada de manera artesanal",
      "parametros_personalizacion": {
        "Unidades": [
          "1",
          "2",
          "3"
        ],
        "material": [
          "madera",
          "metal"
        ],
        "tamanio": [
          "Grande",
          "Mediano",
          "Pequeño"
        ],
        "gravado": "Detalles de gravado para el producto 1"
      },
      "tamaño": 10,
      "input_text": "Elige las unidades",
      "gravado": "Detalles de gravado para el producto 1",
      "categoria": "Alimento",
      "imagen": "src/images/mielAbeja.png",
      "imagenes_detalle": [
        "src/images/mate1.png"
      ],
      "autor": "LeonidasOr",
      "caracteristicas": [
        {
          "caracteristica_1": "ORIGEN: SIERRA PERUANA."
        },
        {
          "caracteristica_2": "FLORACIÓN: En su mayoría la abeja polinizan flores de eucalipto, muña, papa y flores silvestres de la zona."
        },
        {
          "caracteristica_3": "INGREDIENTES: 100% miel de abeja"
        },
        {
          "caracteristica_4": "PRESENTACIÓN: 750gr."
        },
        {
          "caracteristica_5": "Contiene todos los componentes de la mierl rela: polen, propóleo, cera, jalea real, enzimas vivas."
        }
      ]
    }
  ],
  "boletas": [
    {
      "id": "b3f3",
      "productId": "prd01",
      "product": "Mate Burilado",
      "parameters": {},
      "price": 35
    },
    {
      "id": "5eb9",
      "productId": "prd02",
      "product": "Miel de abeja  ",
      "parameters": {},
      "price": 25
    },
    {
      "id": "c295",
      "productId": "prd01",
      "product": "Mate Burilado",
      "parameters": {},
      "price": 50
    },
    {
      "id": "e585",
      "productId": "prd02",
      "product": "Miel de abeja  ",
      "parameters": {},
      "price": 20
    },
    {
      "id": "7a30",
      "productId": "prd02",
      "product": "Miel de abeja  ",
      "parameters": {},
      "price": 50
    },
    {
      "id": "28da",
      "productId": "prd02",
      "product": "Miel de abeja  ",
      "parameters": {},
      "price": 27.5
    },
    {
      "id": "a21a",
      "productId": "prd01",
      "product": "Mate Burilado",
      "parameters": {},
      "price": 16.5
    }
  ],
  "productos_caracteristicas": [
    {
      "color": [
        "rojo",
        "verde",
        "amarillo",
        "azul",
        "anaranjado",
        "morado",
        "marron",
        "celeste",
        "negro",
        "rosado"
      ],
      "tamaño": [
        "pequeño",
        "mediano",
        "grande"
      ],
      "material": [
        "madera",
        "tela",
        "ceramica",
        "acero",
        "vidrio",
        "barro",
        "cestería"
      ],
      "categoria": [
        "Joyería artesanal",
        "Textiles y tejidos",
        "Cerámica y alfarería",
        "Artesanía en madera",
        "Artesanía en cuero",
        "Arte visual",
        "Cuidado personal",
        "Juguetes",
        "Decoración del hogar",
        "Productos gastronómicos artesanales"
      ]
    }
  ],
  "producto_publicado": [
    {
      "id": 1,
      "color": [
        "rojo",
        "verde"
      ],
      "tamaño": [
        "grande",
        "pequeño"
      ],
      "material": "madera",
      "nombre": "picocho",
      "categoria": "artesano madera",
      "precio": 150,
      "descripcion": "pinocho con cara feliz"
    },
    {
      "id": 0,
      "color": [],
      "tamaño": [],
      "material": "",
      "nombre": "producto 0",
      "categoria": "Textiles y tejidos",
      "precio": 25,
      "descripcion": "descripcion del producto 0"
    },
    {
      "id": 0,
      "color": [
        "rojo",
        "verde",
        "amarillo"
      ],
      "tamaño": [
        "pequeño",
        "mediano"
      ],
      "material": "madera"
    },
    {
      "id": 0,
      "color": [],
      "tamaño": [],
      "material": "",
      "nombre": "",
      "categoria": "",
      "precio": null
    }
  ]
}